pwnkit/__init__.py
pwnkit/__main__.py
pwnkit/_version.py
pwnkit/config.py
pwnkit/ctx.py
pwnkit/decors.py
pwnkit/encrypt.py
pwnkit/gdbx.py
pwnkit/hashpow.py
pwnkit/iofiles.py
pwnkit/rc4.py
pwnkit/rop.py
pwnkit/shellcode.py
pwnkit/ucontext.py
pwnkit/utils.py
pwnkit/templates/default.py.tpl
pwnkit/templates/full.py.tpl
pwnkit/templates/got.py.tpl
pwnkit/templates/heap.py.tpl
pwnkit/templates/iofile.py.tpl
pwnkit/templates/minimal.py.tpl
pwnkit/templates/ret2libc.py.tpl
pwnkit/templates/ret2syscall.py.tpl
pwnkit/templates/setcontext.py.tpl
pwnkit/templates/srop.py.tpl
pwnkit-0.2.20.dist-info/METADATA
pwnkit-0.2.20.dist-info/WHEEL
pwnkit-0.2.20.dist-info/entry_points.txt
pwnkit-0.2.20.dist-info/licenses/LICENSE
pwnkit-0.2.20.dist-info/RECORD
